fetchtube/__init__.py
fetchtube/fetchtube.py
fetchtube-2023.11.1.2.dist-info/METADATA
fetchtube-2023.11.1.2.dist-info/WHEEL
fetchtube-2023.11.1.2.dist-info/entry_points.txt
fetchtube-2023.11.1.2.dist-info/licenses/LICENSE.txt
fetchtube-2023.11.1.2.dist-info/RECORD
