Metadata-Version: 2.1
Name: fetchtube
Version: 2023.11.1.2
Summary: A simple package to download YouTube audio/video
Project-URL: Homepage, https://github.com/fyresmith/fetchtube
Project-URL: Bug Tracker, https://github.com/fyresmith/fetchtube/issues
Author-email: Caleb Smith <me@calebmsmith.com>
Maintainer-email: Caleb Smith <me@calebmsmith.com>
License: MIT License
License-File: LICENSE.txt
Keywords: audio,downloader,video,youtube
Classifier: Development Status :: 4 - Beta
Classifier: License :: OSI Approved :: MIT License
Classifier: Operating System :: OS Independent
Classifier: Programming Language :: Python :: 3
Requires-Python: >=3.8
Requires-Dist: pytube
